SmolPyGUI/__init__.py
SmolPyGUI/core.py
SmolPyGUI/fonts/CourierPrime-Italic.ttf
SmolPyGUI/fonts/CourierPrime-Regular.ttf
SmolPyGUI/fonts/RobotoMono-Italic.ttf
SmolPyGUI/fonts/RobotoMono-Regular.ttf
smolpygui-1.64.4.dist-info/licenses/LICENSE
smolpygui-1.64.4.dist-info/METADATA
smolpygui-1.64.4.dist-info/WHEEL
smolpygui-1.64.4.dist-info/top_level.txt
smolpygui-1.64.4.dist-info/RECORD
