Metadata-Version: 2.4
Name: SmolPyGUI
Version: 1.64.4
Summary: A little GUI system made with pygame
Author-email: Smol <kingalexander471@gmail.com>
License: MIT
Requires-Python: >=3.12
License-File: LICENSE
Requires-Dist: pygame>=2.6.1
Dynamic: license-file
